{
  "modelVersion" : "2.2",
  "id" : "modificarDocEntregaTesisTerminada",
  "name" : "modificarDocEntregaTesisTerminada",
  "lastUpdate" : 1655908577510,
  "rows" : [
    [
      {
        "type" : "container",
        "dimension" : {
          "xs" : 12
        },
        "propertyValues" : { },
        "reference" : "6eb6d425-a44a-4c99-995d-a9ccdeb8b973",
        "hasValidationError" : false,
        "id" : "pbContainer",
        "rows" : [
          [
            {
              "type" : "component",
              "dimension" : {
                "md" : 12,
                "sm" : 12,
                "xs" : 12,
                "lg" : 12
              },
              "propertyValues" : {
                "hidden" : {
                  "type" : "constant",
                  "value" : false
                },
                "level" : {
                  "type" : "constant",
                  "value" : "Level 1"
                },
                "cssClasses" : {
                  "type" : "constant",
                  "value" : ""
                },
                "text" : {
                  "type" : "interpolation",
                  "value" : "Modificar los documentos de entrega del trabajo de titulación terminado"
                },
                "alignment" : {
                  "type" : "constant",
                  "value" : "center"
                },
                "dimension" : {
                  "type" : "constant",
                  "value" : 12
                }
              },
              "reference" : "98dba149-43d2-439c-94af-87c8ef2066ba",
              "hasValidationError" : false,
              "id" : "pbTitle",
              "description" : ""
            }
          ],
          [
            {
              "type" : "component",
              "dimension" : {
                "md" : 12,
                "sm" : 12,
                "xs" : 12,
                "lg" : 12
              },
              "propertyValues" : {
                "allowHtml" : {
                  "type" : "constant",
                  "value" : true
                },
                "labelHidden" : {
                  "type" : "constant",
                  "value" : true
                },
                "hidden" : {
                  "type" : "constant",
                  "value" : false
                },
                "cssClasses" : {
                  "type" : "constant",
                  "value" : ""
                },
                "label" : {
                  "type" : "interpolation"
                },
                "text" : {
                  "type" : "interpolation",
                  "value" : "<i> Estimado(a) estudiante, la documentación o información proporcionada contiene algunos errores que deben revisarse, sírvase del comentario emitido por el analista de titulación para solucionarlos, una vez realizado los cambios ingrese la información y la documentación nuevamente.</i>"
                },
                "alignment" : {
                  "type" : "constant",
                  "value" : "left"
                },
                "dimension" : {
                  "type" : "constant",
                  "value" : 12
                },
                "labelPosition" : {
                  "type" : "constant",
                  "value" : "top"
                },
                "labelWidth" : {
                  "type" : "constant",
                  "value" : 4
                },
                "allowHTML" : {
                  "type" : "constant",
                  "value" : true
                }
              },
              "reference" : "00d26d9b-0eb6-4717-9274-02c236694c80",
              "hasValidationError" : false,
              "id" : "pbText",
              "description" : ""
            }
          ]
        ]
      }
    ],
    [
      {
        "type" : "formContainer",
        "dimension" : {
          "xs" : 12
        },
        "propertyValues" : {
          "cssClasses" : {
            "type" : "constant",
            "value" : ""
          },
          "hidden" : {
            "type" : "constant",
            "value" : false
          }
        },
        "reference" : "51a01508-7450-45f5-b13e-18eae8302647",
        "hasValidationError" : false,
        "id" : "pbFormContainer",
        "container" : {
          "type" : "container",
          "dimension" : {
            "xs" : 12
          },
          "propertyValues" : { },
          "reference" : "b3a9ece1-3860-471e-8a7a-ab305b3e57fc",
          "hasValidationError" : false,
          "id" : "pbContainer",
          "rows" : [
            [
              {
                "type" : "component",
                "dimension" : {
                  "xs" : 12,
                  "sm" : 12,
                  "md" : 12,
                  "lg" : 12
                },
                "propertyValues" : {
                  "cssClasses" : {
                    "type" : "constant",
                    "value" : ""
                  },
                  "hidden" : {
                    "type" : "constant",
                    "value" : false
                  },
                  "labelHidden" : {
                    "type" : "constant",
                    "value" : true
                  },
                  "label" : {
                    "type" : "interpolation",
                    "value" : "Default label"
                  },
                  "labelPosition" : {
                    "type" : "constant",
                    "value" : "top"
                  },
                  "labelWidth" : {
                    "type" : "constant",
                    "value" : 4
                  },
                  "allowHTML" : {
                    "type" : "constant",
                    "value" : true
                  },
                  "text" : {
                    "type" : "interpolation",
                    "value" : "<b>Comentario explicativo de las modificaciones a realizarse</b>\n<br>{{titulacion.coment_docu_entregatrabajo_titulacion}}\n{{datos}}"
                  },
                  "alignment" : {
                    "type" : "constant",
                    "value" : "left"
                  }
                },
                "reference" : "c203dfd5-3446-4dd4-8d61-bdda6efa0278",
                "hasValidationError" : false,
                "id" : "pbText"
              }
            ],
            [
              {
                "type" : "container",
                "dimension" : {
                  "md" : 12,
                  "sm" : 12,
                  "xs" : 12,
                  "lg" : 12
                },
                "propertyValues" : {
                  "repeatedCollection" : {
                    "type" : "variable"
                  },
                  "hidden" : {
                    "type" : "constant",
                    "value" : false
                  },
                  "cssClasses" : {
                    "type" : "constant",
                    "value" : ""
                  },
                  "dimension" : {
                    "type" : "constant",
                    "value" : 12
                  }
                },
                "reference" : "7a43b7fa-8895-4a17-b490-96fb9bf76153",
                "hasValidationError" : false,
                "id" : "pbContainer",
                "rows" : [
                  [
                    {
                      "type" : "component",
                      "dimension" : {
                        "xs" : 12,
                        "sm" : 12,
                        "md" : 12,
                        "lg" : 12
                      },
                      "propertyValues" : {
                        "cssClasses" : {
                          "type" : "constant",
                          "value" : ""
                        },
                        "hidden" : {
                          "type" : "constant",
                          "value" : false
                        },
                        "readOnly" : {
                          "type" : "constant",
                          "value" : true
                        },
                        "required" : {
                          "type" : "constant",
                          "value" : false
                        },
                        "minLength" : {
                          "type" : "constant",
                          "value" : ""
                        },
                        "maxLength" : {
                          "type" : "constant",
                          "value" : ""
                        },
                        "labelHidden" : {
                          "type" : "constant",
                          "value" : false
                        },
                        "label" : {
                          "type" : "interpolation",
                          "value" : "Tema del trabajo de titulación"
                        },
                        "labelPosition" : {
                          "type" : "constant",
                          "value" : "left"
                        },
                        "labelWidth" : {
                          "type" : "constant",
                          "value" : 4
                        },
                        "value" : {
                          "type" : "variable",
                          "value" : "titulacion.tema_tesis"
                        }
                      },
                      "reference" : "9a0e8488-56b3-4f88-ae3f-a2cc0d3d98b1",
                      "hasValidationError" : false,
                      "id" : "pbTextarea"
                    }
                  ],
                  [
                    {
                      "type" : "component",
                      "dimension" : {
                        "md" : 12,
                        "sm" : 12,
                        "xs" : 12,
                        "lg" : 12
                      },
                      "propertyValues" : {
                        "hidden" : {
                          "type" : "constant",
                          "value" : false
                        },
                        "level" : {
                          "type" : "constant",
                          "value" : "Level 4"
                        },
                        "cssClasses" : {
                          "type" : "constant",
                          "value" : ""
                        },
                        "text" : {
                          "type" : "interpolation",
                          "value" : "Documentación a entregar del trabajo de titulación terminado"
                        },
                        "alignment" : {
                          "type" : "constant",
                          "value" : "left"
                        },
                        "dimension" : {
                          "type" : "constant",
                          "value" : 12
                        }
                      },
                      "reference" : "ab936d8d-17b6-4b61-86f2-1fad0ad6254e",
                      "hasValidationError" : false,
                      "id" : "pbTitle",
                      "description" : ""
                    }
                  ],
                  [
                    {
                      "type" : "component",
                      "dimension" : {
                        "xs" : 12,
                        "sm" : 12,
                        "md" : 12,
                        "lg" : 12
                      },
                      "propertyValues" : {
                        "cssClasses" : {
                          "type" : "constant",
                          "value" : ""
                        },
                        "hidden" : {
                          "type" : "constant",
                          "value" : false
                        },
                        "required" : {
                          "type" : "constant",
                          "value" : false
                        },
                        "labelHidden" : {
                          "type" : "constant",
                          "value" : false
                        },
                        "label" : {
                          "type" : "interpolation",
                          "value" : "Solicitud dirigida al director/a de carrera"
                        },
                        "labelPosition" : {
                          "type" : "constant",
                          "value" : "left"
                        },
                        "labelWidth" : {
                          "type" : "constant",
                          "value" : 4
                        },
                        "placeholder" : {
                          "type" : "interpolation"
                        },
                        "url" : {
                          "type" : "constant",
                          "value" : "../API/formFileUpload"
                        },
                        "value" : {
                          "type" : "variable",
                          "value" : "context.doc_solicitud_terminacion_tesis_ref.newValue"
                        },
                        "errorContent" : {
                          "type" : "variable",
                          "value" : ""
                        }
                      },
                      "reference" : "d2bdbee7-e914-43f7-bc18-f4503ded6c0b",
                      "hasValidationError" : false,
                      "id" : "pbUpload"
                    }
                  ],
                  [
                    {
                      "type" : "component",
                      "dimension" : {
                        "xs" : 12,
                        "sm" : 12,
                        "md" : 12,
                        "lg" : 12
                      },
                      "propertyValues" : {
                        "cssClasses" : {
                          "type" : "constant",
                          "value" : ""
                        },
                        "hidden" : {
                          "type" : "constant",
                          "value" : false
                        },
                        "required" : {
                          "type" : "constant",
                          "value" : false
                        },
                        "labelHidden" : {
                          "type" : "constant",
                          "value" : false
                        },
                        "label" : {
                          "type" : "interpolation",
                          "value" : "Informes anti-plagio"
                        },
                        "labelPosition" : {
                          "type" : "constant",
                          "value" : "left"
                        },
                        "labelWidth" : {
                          "type" : "constant",
                          "value" : 4
                        },
                        "placeholder" : {
                          "type" : "interpolation"
                        },
                        "url" : {
                          "type" : "constant",
                          "value" : "../API/formFileUpload"
                        },
                        "value" : {
                          "type" : "variable",
                          "value" : "context.doc_antiplagio_aprob_seguimiento_ref.newValue"
                        },
                        "errorContent" : {
                          "type" : "variable",
                          "value" : ""
                        }
                      },
                      "reference" : "98366126-baf5-4a25-aea8-a11ffe714aa6",
                      "hasValidationError" : false,
                      "id" : "pbUpload"
                    }
                  ],
                  [
                    {
                      "type" : "component",
                      "dimension" : {
                        "xs" : 12,
                        "sm" : 12,
                        "md" : 12,
                        "lg" : 12
                      },
                      "propertyValues" : {
                        "cssClasses" : {
                          "type" : "constant",
                          "value" : ""
                        },
                        "hidden" : {
                          "type" : "constant",
                          "value" : false
                        },
                        "required" : {
                          "type" : "constant",
                          "value" : false
                        },
                        "labelHidden" : {
                          "type" : "constant",
                          "value" : false
                        },
                        "label" : {
                          "type" : "interpolation",
                          "value" : "Informe de seguimiento emitido por el tutor"
                        },
                        "labelPosition" : {
                          "type" : "constant",
                          "value" : "left"
                        },
                        "labelWidth" : {
                          "type" : "constant",
                          "value" : 4
                        },
                        "placeholder" : {
                          "type" : "interpolation"
                        },
                        "url" : {
                          "type" : "constant",
                          "value" : "../API/formFileUpload"
                        },
                        "value" : {
                          "type" : "variable",
                          "value" : "context.seguimiento_emitido_tutor_ref.newValue"
                        },
                        "errorContent" : {
                          "type" : "variable",
                          "value" : ""
                        }
                      },
                      "reference" : "2f2d0bac-00f9-4778-8e41-83550c16bb6f",
                      "hasValidationError" : false,
                      "id" : "pbUpload"
                    }
                  ],
                  [
                    {
                      "type" : "component",
                      "dimension" : {
                        "xs" : 12,
                        "sm" : 12,
                        "md" : 12,
                        "lg" : 12
                      },
                      "propertyValues" : {
                        "cssClasses" : {
                          "type" : "constant",
                          "value" : ""
                        },
                        "hidden" : {
                          "type" : "constant",
                          "value" : false
                        },
                        "required" : {
                          "type" : "constant",
                          "value" : false
                        },
                        "labelHidden" : {
                          "type" : "constant",
                          "value" : false
                        },
                        "label" : {
                          "type" : "interpolation",
                          "value" : "Trabajo de titulación terminado"
                        },
                        "labelPosition" : {
                          "type" : "constant",
                          "value" : "left"
                        },
                        "labelWidth" : {
                          "type" : "constant",
                          "value" : 4
                        },
                        "placeholder" : {
                          "type" : "interpolation"
                        },
                        "url" : {
                          "type" : "constant",
                          "value" : "../API/formFileUpload"
                        },
                        "value" : {
                          "type" : "variable",
                          "value" : "context.doc_trabajo_titulacion_ref.newValue"
                        },
                        "errorContent" : {
                          "type" : "variable",
                          "value" : ""
                        }
                      },
                      "reference" : "cf308154-ece7-4bf0-802d-789086b68cd7",
                      "hasValidationError" : false,
                      "id" : "pbUpload"
                    }
                  ]
                ]
              }
            ],
            [
              {
                "type" : "component",
                "dimension" : {
                  "md" : 12,
                  "sm" : 12,
                  "xs" : 12,
                  "lg" : 12
                },
                "propertyValues" : {
                  "removeItem" : {
                    "type" : "variable"
                  },
                  "hidden" : {
                    "type" : "constant",
                    "value" : false
                  },
                  "cssClasses" : {
                    "type" : "constant",
                    "value" : ""
                  },
                  "buttonStyle" : {
                    "type" : "constant",
                    "value" : "primary"
                  },
                  "label" : {
                    "type" : "interpolation",
                    "value" : "Submit"
                  },
                  "dataToSend" : {
                    "type" : "expression",
                    "value" : "formOutput"
                  },
                  "dataFromError" : {
                    "type" : "variable",
                    "value" : "formOutput._submitError"
                  },
                  "labelHidden" : {
                    "type" : "constant",
                    "value" : false
                  },
                  "collectionPosition" : {
                    "type" : "constant"
                  },
                  "targetUrlOnSuccess" : {
                    "type" : "interpolation",
                    "value" : "/bonita"
                  },
                  "action" : {
                    "type" : "constant",
                    "value" : "Submit task"
                  },
                  "collectionToModify" : {
                    "type" : "variable"
                  },
                  "valueToAdd" : {
                    "type" : "expression"
                  },
                  "disabled" : {
                    "type" : "expression",
                    "value" : "$form.$invalid"
                  },
                  "alignment" : {
                    "type" : "constant",
                    "value" : "center"
                  },
                  "dimension" : {
                    "type" : "constant",
                    "value" : 12
                  }
                },
                "reference" : "78f51cc4-f46e-46e1-a309-1dd3593d7bc8",
                "hasValidationError" : false,
                "id" : "pbButton",
                "description" : ""
              }
            ],
            [
              {
                "type" : "component",
                "dimension" : {
                  "md" : 12,
                  "sm" : 12,
                  "xs" : 12,
                  "lg" : 12
                },
                "propertyValues" : {
                  "allowHTML" : {
                    "type" : "constant",
                    "value" : true
                  },
                  "allowHtml" : {
                    "type" : "constant",
                    "value" : true
                  },
                  "labelHidden" : {
                    "type" : "constant",
                    "value" : true
                  },
                  "hidden" : {
                    "type" : "expression",
                    "value" : "!formOutput._submitError.message"
                  },
                  "cssClasses" : {
                    "type" : "constant",
                    "value" : "alert alert-danger col-lg-6 col-lg-offset-3"
                  },
                  "label" : {
                    "type" : "interpolation"
                  },
                  "text" : {
                    "type" : "interpolation",
                    "value" : "<strong>Debug message</strong>\n<br/>\n{{formOutput._submitError.message}}\n{{submit_errors_list}}"
                  },
                  "alignment" : {
                    "type" : "constant",
                    "value" : "left"
                  },
                  "dimension" : {
                    "type" : "constant",
                    "value" : 12
                  }
                },
                "reference" : "389af2f4-8ac6-4cd3-9c7b-5be1a949a6a9",
                "hasValidationError" : false,
                "id" : "pbText",
                "description" : ""
              }
            ]
          ]
        }
      }
    ]
  ],
  "assets" : [
    {
      "id" : "c2217348-9828-42c5-bc91-f1a09f05880a",
      "name" : "style.css",
      "type" : "css",
      "order" : 0,
      "external" : false
    },
    {
      "id" : "5005669c-c8a3-4fa3-8855-df411959be5a",
      "name" : "localization.json",
      "type" : "json",
      "order" : 0,
      "external" : false
    }
  ],
  "inactiveAssets" : [ ],
  "variables" : {
    "task" : {
      "type" : "url",
      "value" : [
        "../API/bpm/userTask/{{taskId}}"
      ],
      "exposed" : false
    },
    "submit_errors_list" : {
      "type" : "expression",
      "value" : [
        "if($data.formOutput && $data.formOutput._submitError && $data.formOutput._submitError.explanations){",
        "\tconst liElements = $data.formOutput._submitError.explanations",
        "\t\t.filter(cause => cause !== null)",
        "\t\t.map(cause => \"<li>\" + cause + \"</li>\")",
        "\t\t.join('');",
        "\tif(liElements){",
        "\t\treturn \"<ul>\" + liElements + \"</ul>\";",
        "\t}",
        "}"
      ],
      "exposed" : false
    },
    "formOutput" : {
      "type" : "expression",
      "value" : [
        "if( $data.context ){",
        "\treturn {",
        "\t\tdoc_solicitud_terminacion_tesisDocumentInput: {",
        "\t\t\tid: $data.context.doc_solicitud_terminacion_tesis_ref && $data.context.doc_solicitud_terminacion_tesis_ref.id ? $data.context.doc_solicitud_terminacion_tesis_ref.id.toString() : null,",
        "\t\t\tfilename: $data.context.doc_solicitud_terminacion_tesis_ref.newValue && $data.context.doc_solicitud_terminacion_tesis_ref.newValue.filename ? $data.context.doc_solicitud_terminacion_tesis_ref.newValue.filename : null,",
        "\t\t\ttempPath: $data.context.doc_solicitud_terminacion_tesis_ref.newValue && $data.context.doc_solicitud_terminacion_tesis_ref.newValue.tempPath ? $data.context.doc_solicitud_terminacion_tesis_ref.newValue.tempPath : null,",
        "\t\t\tcontentType: $data.context.doc_solicitud_terminacion_tesis_ref.newValue && $data.context.doc_solicitud_terminacion_tesis_ref.newValue.contentType ? $data.context.doc_solicitud_terminacion_tesis_ref.newValue.contentType : null",
        "\t\t},",
        "\t\tdoc_antiplagio_aprob_seguimientoDocumentInput: {",
        "\t\t\tid: $data.context.doc_antiplagio_aprob_seguimiento_ref && $data.context.doc_antiplagio_aprob_seguimiento_ref.id ? $data.context.doc_antiplagio_aprob_seguimiento_ref.id.toString() : null,",
        "\t\t\tfilename: $data.context.doc_antiplagio_aprob_seguimiento_ref.newValue && $data.context.doc_antiplagio_aprob_seguimiento_ref.newValue.filename ? $data.context.doc_antiplagio_aprob_seguimiento_ref.newValue.filename : null,",
        "\t\t\ttempPath: $data.context.doc_antiplagio_aprob_seguimiento_ref.newValue && $data.context.doc_antiplagio_aprob_seguimiento_ref.newValue.tempPath ? $data.context.doc_antiplagio_aprob_seguimiento_ref.newValue.tempPath : null,",
        "\t\t\tcontentType: $data.context.doc_antiplagio_aprob_seguimiento_ref.newValue && $data.context.doc_antiplagio_aprob_seguimiento_ref.newValue.contentType ? $data.context.doc_antiplagio_aprob_seguimiento_ref.newValue.contentType : null",
        "\t\t},",
        "\t\tdoc_trabajo_titulacionDocumentInput: {",
        "\t\t\tid: $data.context.doc_trabajo_titulacion_ref && $data.context.doc_trabajo_titulacion_ref.id ? $data.context.doc_trabajo_titulacion_ref.id.toString() : null,",
        "\t\t\tfilename: $data.context.doc_trabajo_titulacion_ref.newValue && $data.context.doc_trabajo_titulacion_ref.newValue.filename ? $data.context.doc_trabajo_titulacion_ref.newValue.filename : null,",
        "\t\t\ttempPath: $data.context.doc_trabajo_titulacion_ref.newValue && $data.context.doc_trabajo_titulacion_ref.newValue.tempPath ? $data.context.doc_trabajo_titulacion_ref.newValue.tempPath : null,",
        "\t\t\tcontentType: $data.context.doc_trabajo_titulacion_ref.newValue && $data.context.doc_trabajo_titulacion_ref.newValue.contentType ? $data.context.doc_trabajo_titulacion_ref.newValue.contentType : null",
        "\t\t},",
        "\t\tseguimiento_emitido_tutorDocumentInput: {",
        "\t\t\tid: $data.context.seguimiento_emitido_tutor_ref && $data.context.seguimiento_emitido_tutor_ref.id ? $data.context.seguimiento_emitido_tutor_ref.id.toString() : null,",
        "\t\t\tfilename: $data.context.seguimiento_emitido_tutor_ref.newValue && $data.context.seguimiento_emitido_tutor_ref.newValue.filename ? $data.context.seguimiento_emitido_tutor_ref.newValue.filename : null,",
        "\t\t\ttempPath: $data.context.seguimiento_emitido_tutor_ref.newValue && $data.context.seguimiento_emitido_tutor_ref.newValue.tempPath ? $data.context.seguimiento_emitido_tutor_ref.newValue.tempPath : null,",
        "\t\t\tcontentType: $data.context.seguimiento_emitido_tutor_ref.newValue && $data.context.seguimiento_emitido_tutor_ref.newValue.contentType ? $data.context.seguimiento_emitido_tutor_ref.newValue.contentType : null",
        "\t\t}",
        "\t}",
        "}"
      ],
      "exposed" : false
    },
    "context" : {
      "type" : "url",
      "value" : [
        "../API/bpm/userTask/{{taskId}}/context"
      ],
      "exposed" : false
    },
    "taskId" : {
      "type" : "urlparameter",
      "value" : [
        "id"
      ],
      "exposed" : false
    }
  },
  "hasValidationError" : false,
  "uuid" : "357d7680-1012-4b86-bccd-c84bd87daa96",
  "type" : "form",
  "description" : "Page generated with Bonita UI designer"
}